{
  "uuid": "9ef15917-e011-4698-9281-cebfc9547262",
  "name": "Saby_ДанныеТитулов",
  "name2": {
    "ru": "SABY Данные титулов"
  },
  "comment": "",
  "h1_0": "1",
  "h0": "3",
  "h5": [
    "0",
    "0",
    "00000000-0000-0000-0000-000000000000",
    "0"
  ],
  "data": [
    [
      "1",
      [
        "33",
        "e6c254ed-61ff-4773-80a3-4614e164641b",
        "e898df62-f425-47ef-a1e6-80a6947a8d18",
        "1dbd4a9b-daea-42c0-abc0-c73050abace6",
        "5190a2a8-9a87-4bd6-bb2f-d11c326a9c28",
        "007df5da-4888-4bb6-a3ce-f385ad0454e3",
        "a940fc81-c5d6-4355-ad7f-21f1c1872b1c",
        "6753b5ef-1de5-4f1d-9b80-dc79288df88b",
        "a7164d54-ea79-4bc1-88bd-39f9f86fbe9d",
        "63b007db-3c1c-4831-8890-57abe073dcdd",
        "ca61c761-e35e-4685-bd30-15e562bb596f",
        "fce48dfa-a5ef-4ac1-8432-aae6869671f6",
        "56d69f35-3679-4947-b422-7309f688bef4",
        "134e8e70-31eb-4e2c-a2ff-4d62e44bab7f",
        "59f066c1-c465-487c-9a29-cd41d479a8c9",
        [
          "0",
          [
            "3",
            [
              "1",
              "0",
              "9ef15917-e011-4698-9281-cebfc9547262"
            ],
            "\"Saby_ДанныеТитулов\"",
            [
              "1",
              "\"ru\"",
              "\"SABY Данные титулов\""
            ],
            "\"\"",
            "0",
            "0",
            "00000000-0000-0000-0000-000000000000",
            "0"
          ]
        ],
        "00000000-0000-0000-0000-000000000000",
        "00000000-0000-0000-0000-000000000000",
        "5",
        "0",
        "1",
        "1",
        "0",
        "1",
        "1",
        "0",
        [
          "0"
        ],
        "00000000-0000-0000-0000-000000000000",
        "00000000-0000-0000-0000-000000000000",
        [
          "0"
        ],
        [
          "0"
        ],
        [
          "0"
        ],
        [
          "0"
        ],
        [
          "0"
        ],
        "0",
        "0",
        "0",
        "0",
        "0"
      ],
      "6",
      [
        "13134202-f60b-11d5-a3c7-0050bae0a776",
        "1",
        [
          [
            "7",
            [
              "27",
              [
                "2",
                [
                  "3",
                  [
                    "1",
                    "0",
                    "01ee2844-3adc-422f-b179-f63affb30a7b"
                  ],
                  "\"Данные\"",
                  [
                    "1",
                    "\"ru\"",
                    "\"Данные\""
                  ],
                  "\"\"",
                  "0",
                  "0",
                  "00000000-0000-0000-0000-000000000000",
                  "0"
                ],
                [
                  "\"Pattern\"",
                  [
                    "\"S\""
                  ]
                ]
              ],
              "0",
              [
                "0"
              ],
              [
                "0"
              ],
              "0",
              "\"\"",
              "0",
              [
                "\"U\""
              ],
              [
                "\"U\""
              ],
              "0",
              "00000000-0000-0000-0000-000000000000",
              "2",
              "0",
              [
                "5006",
                "0"
              ],
              [
                "3",
                "0",
                "0"
              ],
              [
                "0",
                "0"
              ],
              "0",
              [
                "0"
              ],
              [
                "\"S\"",
                "\"\""
              ],
              "0",
              "0",
              "0"
            ],
            "0",
            "1",
            "1"
          ],
          "0"
        ]
      ],
      [
        "13134203-f60b-11d5-a3c7-0050bae0a776",
        "4",
        [
          [
            "9",
            [
              "27",
              [
                "2",
                [
                  "3",
                  [
                    "1",
                    "0",
                    "d1b442c8-688c-4d6f-ad09-a6f79936ae68"
                  ],
                  "\"СсылкаНаДокумент\"",
                  [
                    "1",
                    "\"ru\"",
                    "\"Ссылка на документ\""
                  ],
                  "\"\"",
                  "0",
                  "0",
                  "00000000-0000-0000-0000-000000000000",
                  "0"
                ],
                [
                  "\"Pattern\"",
                  [
                    "\"#\"",
                    "79ab653a-8ba3-440b-b573-d6146b55e18e"
                  ],
                  [
                    "\"#\"",
                    "abafa5ce-0cc6-4f5f-982c-51b37aaa9200"
                  ],
                  [
                    "\"#\"",
                    "c9e37337-f4e2-4ca0-96ac-681e5b09c62c"
                  ]
                ]
              ],
              "0",
              [
                "0"
              ],
              [
                "0"
              ],
              "0",
              "\"\"",
              "0",
              [
                "\"U\""
              ],
              [
                "\"U\""
              ],
              "0",
              "00000000-0000-0000-0000-000000000000",
              "2",
              "0",
              [
                "5006",
                "0"
              ],
              [
                "3",
                "0",
                "0"
              ],
              [
                "0",
                "0"
              ],
              "0",
              [
                "0"
              ],
              [
                "\"U\""
              ],
              "1",
              "0",
              "0"
            ],
            "1",
            "0",
            "0",
            "1",
            "1",
            "1"
          ],
          "0"
        ],
        [
          [
            "9",
            [
              "27",
              [
                "2",
                [
                  "3",
                  [
                    "1",
                    "0",
                    "1845357e-d7a8-4c86-8fe7-4d7df86cd801"
                  ],
                  "\"ТипТитула\"",
                  [
                    "1",
                    "\"ru\"",
                    "\"Тип титула\""
                  ],
                  "\"\"",
                  "0",
                  "0",
                  "00000000-0000-0000-0000-000000000000",
                  "0"
                ],
                [
                  "\"Pattern\"",
                  [
                    "\"#\"",
                    "515fd0fe-6bc0-4b2e-b01a-f71f10133624"
                  ],
                  [
                    "\"#\"",
                    "90543f90-2492-4a53-820c-42bc2dedda39"
                  ],
                  [
                    "\"#\"",
                    "e9258e89-47e1-46c4-a786-3b3919acba62"
                  ]
                ]
              ],
              "0",
              [
                "0"
              ],
              [
                "0"
              ],
              "0",
              "\"\"",
              "0",
              [
                "\"U\""
              ],
              [
                "\"U\""
              ],
              "0",
              "00000000-0000-0000-0000-000000000000",
              "2",
              "0",
              [
                "5006",
                "0"
              ],
              [
                "3",
                "0",
                "0"
              ],
              [
                "0",
                "0"
              ],
              "0",
              [
                "0"
              ],
              [
                "\"U\""
              ],
              "0",
              "0",
              "0"
            ],
            "0",
            "0",
            "0",
            "1",
            "1",
            "1"
          ],
          "0"
        ],
        [
          [
            "9",
            [
              "27",
              [
                "2",
                [
                  "3",
                  [
                    "1",
                    "0",
                    "4255cc62-3670-44ef-9116-0faa2de29bb4"
                  ],
                  "\"ИдентификаторТитула\"",
                  [
                    "1",
                    "\"ru\"",
                    "\"Идентификатор титула\""
                  ],
                  "\"\"",
                  "0",
                  "0",
                  "00000000-0000-0000-0000-000000000000",
                  "0"
                ],
                [
                  "\"Pattern\"",
                  [
                    "\"S\"",
                    "36",
                    "1"
                  ]
                ]
              ],
              "0",
              [
                "0"
              ],
              [
                "0"
              ],
              "0",
              "\"\"",
              "0",
              [
                "\"U\""
              ],
              [
                "\"U\""
              ],
              "0",
              "00000000-0000-0000-0000-000000000000",
              "2",
              "0",
              [
                "5006",
                "0"
              ],
              [
                "3",
                "0",
                "0"
              ],
              [
                "0",
                "0"
              ],
              "0",
              [
                "0"
              ],
              [
                "\"S\"",
                "\"\""
              ],
              "0",
              "0",
              "0"
            ],
            "0",
            "0",
            "1",
            "1",
            "1",
            "1"
          ],
          "0"
        ],
        [
          [
            "9",
            [
              "27",
              [
                "2",
                [
                  "3",
                  [
                    "1",
                    "0",
                    "2275b3e4-f95d-42b3-af21-b4bef3bd6b68"
                  ],
                  "\"Основной\"",
                  [
                    "1",
                    "\"ru\"",
                    "\"Основной\""
                  ],
                  "\"\"",
                  "0",
                  "0",
                  "00000000-0000-0000-0000-000000000000",
                  "0"
                ],
                [
                  "\"Pattern\"",
                  [
                    "\"B\""
                  ]
                ]
              ],
              "0",
              [
                "0"
              ],
              [
                "0"
              ],
              "0",
              "\"\"",
              "0",
              [
                "\"U\""
              ],
              [
                "\"U\""
              ],
              "0",
              "00000000-0000-0000-0000-000000000000",
              "2",
              "0",
              [
                "5006",
                "0"
              ],
              [
                "3",
                "0",
                "0"
              ],
              [
                "0",
                "0"
              ],
              "0",
              [
                "0"
              ],
              [
                "\"U\""
              ],
              "0",
              "0",
              "0"
            ],
            "0",
            "0",
            "0",
            "1",
            "1",
            "1"
          ],
          "0"
        ]
      ],
      [
        "13134204-f60b-11d5-a3c7-0050bae0a776",
        "0"
      ],
      [
        "3daea016-69b7-4ed4-9453-127911372fe6",
        "0"
      ],
      [
        "a2207540-1400-11d6-a3c7-0050bae0a776",
        "2",
        [
          [
            "4",
            [
              "27",
              [
                "2",
                [
                  "3",
                  [
                    "1",
                    "0",
                    "52d5d2c0-e014-4c1b-8bc7-cccd39d5f072"
                  ],
                  "\"Просмотрено\"",
                  [
                    "1",
                    "\"ru\"",
                    "\"Просмотрено\""
                  ],
                  "\"\"",
                  "0",
                  "0",
                  "00000000-0000-0000-0000-000000000000",
                  "0"
                ],
                [
                  "\"Pattern\"",
                  [
                    "\"B\""
                  ]
                ]
              ],
              "0",
              [
                "0"
              ],
              [
                "0"
              ],
              "0",
              "\"\"",
              "0",
              [
                "\"U\""
              ],
              [
                "\"U\""
              ],
              "0",
              "00000000-0000-0000-0000-000000000000",
              "2",
              "0",
              [
                "5006",
                "0"
              ],
              [
                "3",
                "0",
                "0"
              ],
              [
                "0",
                "0"
              ],
              "0",
              [
                "0"
              ],
              [
                "\"U\""
              ],
              "0",
              "0",
              "0"
            ],
            "0",
            "0",
            "1"
          ],
          "0"
        ],
        [
          [
            "4",
            [
              "27",
              [
                "2",
                [
                  "3",
                  [
                    "1",
                    "0",
                    "fcb4bf38-b84b-4194-a19f-55464a6b1761"
                  ],
                  "\"ТипТитулаОтказа\"",
                  [
                    "1",
                    "\"ru\"",
                    "\"Тип титула отказа\""
                  ],
                  "\"\"",
                  "0",
                  "0",
                  "00000000-0000-0000-0000-000000000000",
                  "0"
                ],
                [
                  "\"Pattern\"",
                  [
                    "\"#\"",
                    "515fd0fe-6bc0-4b2e-b01a-f71f10133624"
                  ],
                  [
                    "\"#\"",
                    "e9258e89-47e1-46c4-a786-3b3919acba62"
                  ]
                ]
              ],
              "0",
              [
                "0"
              ],
              [
                "0"
              ],
              "0",
              "\"\"",
              "0",
              [
                "\"U\""
              ],
              [
                "\"U\""
              ],
              "0",
              "00000000-0000-0000-0000-000000000000",
              "2",
              "0",
              [
                "5006",
                "0"
              ],
              [
                "3",
                "0",
                "0"
              ],
              [
                "0",
                "0"
              ],
              "0",
              [
                "0"
              ],
              [
                "\"U\""
              ],
              "0",
              "0",
              "0"
            ],
            "0",
            "1",
            "1"
          ],
          "0"
        ]
      ],
      [
        "b44ba719-945c-445c-8aab-1088fa4df16e",
        "0"
      ]
    ]
  ],
  "code_info_mgr": [
    [
      "3",
      "1",
      "0",
      "\"\"",
      "0"
    ]
  ],
  "code_encoding_mgr": "utf-8-sig",
  "code_info_obj": "file",
  "code_encoding_obj": "utf-8"
}